COPYING
MANIFEST.in
README
health_lab_report.xml
health_lab_view.xml
setup.py
./__init__.py
./health_lab.py
./health_lab_report.xml
./health_lab_view.xml
./tryton.cfg
./data/health_lab_sequences.xml
./data/lab_test_data.xml
./doc/index.rst
./icons/execute_icon.svg
./icons/lab_icon.svg
./locale/ar.po
./locale/de.po
./locale/el.po
./locale/es.po
./locale/fr.po
./locale/it_IT.po
./locale/ja_JP.po
./locale/lo.po
./locale/pt_BR.po
./locale/zh_CN.po
./report/__init__.py
./report/labtest.py
./report/labtest_report.odt
./security/access_rights.xml
./tests/__init__.py
./tests/test_health_lab.py
./view/gnuhealth_lab.xml
./view/gnuhealth_lab_test.xml
./view/gnuhealth_lab_test_request_form.xml
./view/gnuhealth_lab_test_request_tree.xml
./view/gnuhealth_lab_test_tree.xml
./view/gnuhealth_lab_tree.xml
./view/gnuhealth_lab_unit_form.xml
./view/gnuhealth_lab_unit_tree.xml
./view/lab_make_test.xml
./view/patient_lab_test_request_start_form.xml
./view/test_critearea_form_lab.xml
./view/test_critearea_form_test_type.xml
./view/test_critearea_tree_lab.xml
./view/test_critearea_tree_test_type.xml
./wizard/__init__.py
./wizard/create_lab_test.xml
./wizard/wizard_create_lab_test.py
data/health_lab_sequences.xml
data/lab_test_data.xml
icons/README
icons/execute_icon.svg
icons/lab_icon.svg
locale/ar.po
locale/de.po
locale/el.po
locale/es.po
locale/fr.po
locale/it_IT.po
locale/ja_JP.po
locale/lo.po
locale/pt_BR.po
locale/zh_CN.po
report/labtest_report.odt
security/access_rights.xml
trytond_health_lab.egg-info/PKG-INFO
trytond_health_lab.egg-info/SOURCES.txt
trytond_health_lab.egg-info/dependency_links.txt
trytond_health_lab.egg-info/entry_points.txt
trytond_health_lab.egg-info/not-zip-safe
trytond_health_lab.egg-info/requires.txt
trytond_health_lab.egg-info/top_level.txt
view/gnuhealth_lab.xml
view/gnuhealth_lab_test.xml
view/gnuhealth_lab_test_request_form.xml
view/gnuhealth_lab_test_request_tree.xml
view/gnuhealth_lab_test_tree.xml
view/gnuhealth_lab_tree.xml
view/gnuhealth_lab_unit_form.xml
view/gnuhealth_lab_unit_tree.xml
view/lab_make_test.xml
view/patient_lab_test_request_start_form.xml
view/test_critearea_form_lab.xml
view/test_critearea_form_test_type.xml
view/test_critearea_tree_lab.xml
view/test_critearea_tree_test_type.xml
wizard/create_lab_test.xml